LICENSE.md
MANIFEST.in
README.md
requirements.dev.txt
requirements.txt
setup.py
bindings/emlpy_common.hpp
emlearn/VERSION.txt
emlearn/__init__.py
emlearn/bayes.py
emlearn/cgen.py
emlearn/common.py
emlearn/convert.py
emlearn/creserved.py
emlearn/distance.py
emlearn/eml_array.h
emlearn/eml_audio.h
emlearn/eml_bayes.h
emlearn/eml_benchmark.h
emlearn/eml_common.h
emlearn/eml_distance.h
emlearn/eml_fft.h
emlearn/eml_fixedpoint.h
emlearn/eml_iir.h
emlearn/eml_log.h
emlearn/eml_mixture.h
emlearn/eml_neighbors.h
emlearn/eml_net.h
emlearn/eml_net_common.h
emlearn/eml_net_fixedpoint.h
emlearn/eml_qsort.h
emlearn/eml_quantizer.h
emlearn/eml_test.h
emlearn/eml_trees.h
emlearn/eml_vector.h
emlearn/fixedpoint.py
emlearn/mixture.py
emlearn/neighbors.py
emlearn/net.py
emlearn/signal.py
emlearn/trees.py
emlearn.egg-info/PKG-INFO
emlearn.egg-info/SOURCES.txt
emlearn.egg-info/dependency_links.txt
emlearn.egg-info/entry_points.txt
emlearn.egg-info/not-zip-safe
emlearn.egg-info/requires.txt
emlearn.egg-info/top_level.txt
emlearn/arduino/install.py
emlearn/evaluate/pareto.py
emlearn/evaluate/size.py
emlearn/evaluate/trees.py
emlearn/preprocessing/__init__.py
emlearn/preprocessing/quantizer.py
emlearn/templates/net_fixedpoint.jinja
emlearn/templates/net_float.jinja
emlearn/tools/__init__.py
emlearn/tools/mel_filterbank.py
emlearn/tools/window_function.py
emlearn/utils/fileutils.py
test/test_arduino.py
test/test_audio.py
test/test_bayes.py
test/test_benchmark.py
test/test_c.py
test/test_cgen.py
test/test_evaluate_size.py
test/test_filters.py
test/test_fixedpoint.py
test/test_mixture.py
test/test_neighbors.py
test/test_net.py
test/test_quantizer.py
test/test_trees.py
test/test_window_function.py
test/test_zephyr.py