Metadata-Version: 2.1
Name: emlearn
Version: 0.23.0
Summary: Machine learning for microcontrollers and embedded systems
Home-page: https://github.com/emlearn/emlearn
Author: Jon Nordby
Author-email: jononor@gmail.com
License-File: LICENSE.md
